lesslines/__init__.py
lesslines/data/__init__.py
lesslines/data/generated/__init__.py
lesslines/data/generated/parametric.py
lesslines/data/observed/__init__.py
lesslines/data/observed/physical_pendulum.py
lesslines/data/observed/simple_pendulum.py
lesslines/math/__init__.py
lesslines/math/interpolation.py
lesslines/math/polynomial.py
lesslines/math/vector.py
lesslines/misc/__init__.py
lesslines/misc/info.py
lesslines/phys/__init__.py
lesslines/phys/piecewise.py
lesslines-0.0.4.dist-info/LICENSE
lesslines-0.0.4.dist-info/METADATA
lesslines-0.0.4.dist-info/WHEEL
lesslines-0.0.4.dist-info/top_level.txt
lesslines-0.0.4.dist-info/RECORD
